valkey/__init__.py
valkey/_cache.py
valkey/backoff.py
valkey/client.py
valkey/cluster.py
valkey/connection.py
valkey/crc.py
valkey/credentials.py
valkey/exceptions.py
valkey/lock.py
valkey/ocsp.py
valkey/py.typed
valkey/retry.py
valkey/sentinel.py
valkey/typing.py
valkey/utils.py
valkey/_parsers/__init__.py
valkey/_parsers/base.py
valkey/_parsers/commands.py
valkey/_parsers/encoders.py
valkey/_parsers/helpers.py
valkey/_parsers/libvalkey.py
valkey/_parsers/resp2.py
valkey/_parsers/resp3.py
valkey/_parsers/socket.py
valkey/_parsers/url_parser.py
valkey/asyncio/__init__.py
valkey/asyncio/client.py
valkey/asyncio/cluster.py
valkey/asyncio/connection.py
valkey/asyncio/lock.py
valkey/asyncio/retry.py
valkey/asyncio/sentinel.py
valkey/asyncio/utils.py
valkey/commands/__init__.py
valkey/commands/cluster.py
valkey/commands/core.py
valkey/commands/helpers.py
valkey/commands/sentinel.py
valkey/commands/valkeymodules.py
valkey/commands/bf/__init__.py
valkey/commands/bf/commands.py
valkey/commands/bf/info.py
valkey/commands/graph/__init__.py
valkey/commands/graph/commands.py
valkey/commands/graph/edge.py
valkey/commands/graph/exceptions.py
valkey/commands/graph/execution_plan.py
valkey/commands/graph/node.py
valkey/commands/graph/path.py
valkey/commands/graph/query_result.py
valkey/commands/json/__init__.py
valkey/commands/json/_util.py
valkey/commands/json/commands.py
valkey/commands/json/decoders.py
valkey/commands/json/path.py
valkey/commands/search/__init__.py
valkey/commands/search/_util.py
valkey/commands/search/aggregation.py
valkey/commands/search/commands.py
valkey/commands/search/document.py
valkey/commands/search/field.py
valkey/commands/search/indexDefinition.py
valkey/commands/search/query.py
valkey/commands/search/querystring.py
valkey/commands/search/reducers.py
valkey/commands/search/result.py
valkey/commands/search/suggestion.py
valkey/commands/timeseries/__init__.py
valkey/commands/timeseries/commands.py
valkey/commands/timeseries/info.py
valkey-6.1.1.dist-info/LICENSE
valkey-6.1.1.dist-info/METADATA
valkey-6.1.1.dist-info/WHEEL
valkey-6.1.1.dist-info/top_level.txt
valkey-6.1.1.dist-info/RECORD
