Metadata-Version: 2.1
Name: valkey
Version: 6.1.1
Summary: Python client for Valkey forked from redis-py
Home-page: https://github.com/valkey-io/valkey-py
Author: valkey-py authors
Author-email: valkey-py@lists.valkey.io
License: MIT
Project-URL: Documentation, https://valkey-py.readthedocs.io/en/latest/
Project-URL: Changes, https://github.com/valkey-io/valkey-py/releases
Project-URL: Code, https://github.com/valkey-io/valkey-py
Project-URL: Issue tracker, https://github.com/valkey-io/valkey-py/issues
Keywords: Valkey,key-value store,database
Platform: UNKNOWN
Classifier: Development Status :: 5 - Production/Stable
Classifier: Environment :: Console
Classifier: Intended Audience :: Developers
Classifier: License :: OSI Approved :: MIT License
Classifier: Operating System :: OS Independent
Classifier: Programming Language :: Python
Classifier: Programming Language :: Python :: 3
Classifier: Programming Language :: Python :: 3 :: Only
Classifier: Programming Language :: Python :: 3.9
Classifier: Programming Language :: Python :: 3.10
Classifier: Programming Language :: Python :: 3.11
Classifier: Programming Language :: Python :: 3.12
Classifier: Programming Language :: Python :: 3.13
Classifier: Programming Language :: Python :: Implementation :: CPython
Classifier: Programming Language :: Python :: Implementation :: PyPy
Requires-Python: >=3.9
Provides-Extra: libvalkey
Provides-Extra: ocsp
License-File: LICENSE
